src/interfaces/i2c/i2c_master.v
module i2c_master (
    input wire clk,           // System clock
    input wire rst_n,         // Active-low reset
    input wire start,         // Start condition
    input wire read_write,    // 1 = Read, 0 = Write
    input wire [6:0] slave_addr,  // 7-bit slave address
    input wire [7:0] data_in, // Data to send (for write)
    input wire [6:0] reg_addr, 
    output reg [7:0] data_out,// Received data (for read)
    output reg busy,          // Busy flag
    output reg done,          // Transaction complete flag
    output reg scl,           // Serial Clock Line
    inout wire sda            // Serial Data Line (Bidirectional)
);

    reg [3:0] state;
    reg [7:0] shift_reg;
    reg [3:0] bit_count;

    reg sda_out;
    reg sda_enable_master;
    reg scl_enable;

    assign sda = (sda_enable_master) ? sda_out : 1'bz;  // Open-drain SDA line

    // Control SCL toggling
    always @(posedge clk or negedge rst_n) begin
        if (!rst_n) begin
            scl <= 1;
        end else if (busy) begin
            scl <= ~scl;  // Generate SCL clock when busy
        end
    end

    localparam IDLE  = 4'b0000,
               START = 4'b0001,
               ADDR  = 4'b0010,
               RW    = 4'b0011,
               ACK1  = 4'b0100,
               WRITE = 4'b0101,
               ACK2  = 4'b0110,
               READ  = 4'b0111,
               STOP  = 4'b1000;

    always @(posedge clk or negedge rst_n) begin
        if (!rst_n) begin
            state <= IDLE;
            sda_out <= 1;
            sda_enable_master <= 1;
            busy <= 0;
            done <= 0;
        end else begin
            case (state)
                IDLE: begin
                    busy <= 0;
                    done <= 0;
                    data_out <= 0;
                    if (start) begin
                        state <= START;
                        busy <= 1;
                    end
                end

                START: begin
                    sda_out <= 0; // Start condition
                    sda_enable_master <= 1; 
                    state <= ADDR;
                    shift_reg <= {slave_addr, read_write}; // Address + R/W bit
                    bit_count <= 8;
                end

                ADDR: begin
                    sda_enable_master <= 1;
                    if (bit_count > 0) begin
                        sda_out <= shift_reg[7];
                        shift_reg <= shift_reg << 1;
                        bit_count <= bit_count - 1;
                    end else begin
                        sda_enable_master <= 0; // Release SDA for ACK
                        state <= ACK1;
                    end
                end

                ACK1: begin
                    if (!sda && scl) begin // Slave ACK received
                        state <= (read_write) ? READ : WRITE;
                        shift_reg <= data_in;
                        bit_count <= 8;
                    end
                end

                WRITE: begin
                    if (bit_count > 0) begin
                        sda_enable_master <= 1;
                        sda_out <= shift_reg[7];
                        shift_reg <= shift_reg << 1;
                        bit_count <= bit_count - 1;
                    end else begin
                        sda_enable_master <= 0; // Release SDA for ACK
                        state <= ACK2;
                    end
                end

                ACK2: begin
                    if (!sda && scl) begin // Slave ACK received
                        state <= STOP;
                    end
                end

                READ: begin
                    if (bit_count > 0 && scl) begin
                        sda_enable_master <= 0; // Release SDA for reading
                        data_out <= {data_out[6:0], sda};
                        bit_count <= bit_count - 1;
                    end else if (bit_count == 0) begin
                        state <= STOP;
                    end
                end

                STOP: begin
                    sda_enable_master <= 1;
                    sda_out <= 0;
                    sda_out <= 1; // Stop condition
                    done <= 1;
                    busy <= 0;
                    state <= IDLE;
                end
            endcase
        end
    end

endmodule

tb/interfaces/i2c_tb.v
`timescale 1ns / 1ps
`include "src/interfaces/i2c/i2c_master.v"

module tb_i2c_master;

    reg clk;
    reg rst_n;
    reg start;
    reg read_write;
    reg [6:0] slave_addr;
    reg [7:0] data_in;
    wire [7:0] data_out;
    wire busy, done;
    wire scl;
    wire sda;

    reg sda_slave;   // Simulated slave SDA line
    reg sda_from_slave; 


    // Instantiate I2C Master
    i2c_master uut(
        .clk(clk),
        .rst_n(rst_n),
        .start(start),
        .read_write(read_write),
        .slave_addr(slave_addr),
        .data_in(data_in),
        .data_out(data_out),
        .busy(busy),
        .done(done),
        .scl(scl),
        .sda(sda)
    );

    // Clock generator (100 MHz)
    always #5 clk = ~clk;

    initial begin
        // Initialize signals
        sda_slave = 0; 
        clk = 0;
        rst_n = 0;
        start = 0;
        read_write = 0;
        slave_addr = 7'b1010101; // Example address
        data_in = 8'h3C;
        sda_slave = 0;
        

        #20 rst_n = 1;  // Release reset

        // Read operation
        #50 read_write = 1;
        #10 start = 1;
        #10 start = 0;

        // Simulate data from slave
        #100
        sda_slave = 1; 
        sda_from_slave = 0; // ACK
        #10 sda_from_slave = 1; // Data bit 1
        #10 sda_from_slave = 0; // Data bit 0
        #10 sda_from_slave = 1; // Data bit 0
        #10 sda_from_slave = 1; // Data bit 0
        #10 sda_from_slave = 1; // Data bit 0
        #10 sda_from_slave = 1; // Data bit 0
        #10 sda_from_slave = 0; // Data bit 0
        #10 sda_from_slave = 1; // Stop

        #100
        // sda_slave = 0; 
        // sda_from_slave = 0; 
        #50
        sda_slave = 0; 

        $finish;
    end

    assign sda = (sda_slave) ? sda_from_slave :  1'bz ; // Open-drain emulation

    initial begin:TEST_BENCH
        $dumpfile("i2c_sim.vcd"); 
        $dumpvars(0, uut); 
    end 

endmodule

sim/waves/i2c_sim.vcd
$date
	Sat Mar  1 17:40:18 2025
$end
$version
	Icarus Verilog
$end
$timescale
	1ps
$end
$scope module tb_i2c_master $end
$scope module uut $end
$var wire 1 ! clk $end
$var wire 8 " data_in [7:0] $end
$var wire 1 # read_write $end
$var wire 7 $ reg_addr [6:0] $end
$var wire 1 % rst_n $end
$var wire 1 & sda $end
$var wire 7 ' slave_addr [6:0] $end
$var wire 1 ( start $end
$var parameter 4 ) ACK1 $end
$var parameter 4 * ACK2 $end
$var parameter 4 + ADDR $end
$var parameter 4 , IDLE $end
$var parameter 4 - READ $end
$var parameter 4 . RW $end
$var parameter 4 / START $end
$var parameter 4 0 STOP $end
$var parameter 4 1 WRITE $end
$var reg 4 2 bit_count [3:0] $end
$var reg 1 3 busy $end
$var reg 8 4 data_out [7:0] $end
$var reg 1 5 done $end
$var reg 1 6 scl $end
$var reg 1 7 sda_enable_master $end
$var reg 1 8 sda_out $end
$var reg 8 9 shift_reg [7:0] $end
$var reg 4 : state [3:0] $end
$upscope $end
$upscope $end
$enddefinitions $end
$comment Show the parameter values. $end
$dumpall
b101 1
b1000 0
b1 /
b11 .
b111 -
b0 ,
b10 +
b110 *
b100 )
$end
#0
$dumpvars
b0 :
bx 9
18
17
16
05
bx 4
03
bx 2
0(
b1010101 '
1&
0%
bz $
0#
b111100 "
0!
$end
#5000
1!
#10000
0!
#15000
1!
#20000
0!
1%
#25000
b0 4
1!
#30000
0!
#35000
1!
#40000
0!
#45000
1!
#50000
0!
#55000
1!
#60000
0!
#65000
1!
#70000
0!
1#
#75000
1!
#80000
0!
1(
#85000
13
b1 :
1!
#90000
06
0!
0(
#95000
0&
b1000 2
b10101011 9
b10 :
08
16
1!
#100000
06
0!
#105000
1&
b111 2
b1010110 9
18
16
1!
#110000
06
0!
#115000
0&
b110 2
b10101100 9
08
16
1!
#120000
06
0!
#125000
1&
b101 2
b1011000 9
18
16
1!
#130000
06
0!
#135000
0&
b100 2
b10110000 9
08
16
1!
#140000
06
0!
#145000
1&
b11 2
b1100000 9
18
16
1!
#150000
06
0!
#155000
0&
b10 2
b11000000 9
08
16
1!
#160000
06
0!
#165000
1&
b1 2
b10000000 9
18
16
1!
#170000
06
0!
#175000
b0 2
b0 9
16
1!
#180000
06
0!
#185000
z&
b100 :
07
16
1!
#190000
06
0&
0!
#195000
b1000 2
b111100 9
b111 :
16
1!
#200000
06
1&
0!
#205000
b111 2
b1 4
16
1!
#210000
06
0&
0!
#215000
b110 2
b10 4
16
1!
#220000
06
1&
0!
#225000
b101 2
b101 4
16
1!
#230000
06
0!
#235000
b100 2
b1011 4
16
1!
#240000
06
0!
#245000
b11 2
b10111 4
16
1!
#250000
06
0!
#255000
b10 2
b101111 4
16
1!
#260000
06
0&
0!
#265000
b1 2
b1011110 4
16
1!
#270000
06
1&
0!
#275000
b0 2
b10111101 4
16
1!
#280000
06
0!
#285000
b1000 :
16
1!
#290000
06
0!
#295000
b0 :
03
15
18
17
16
1!
#300000
0!
#305000
b0 4
05
1!
