src/interfaces/i2c/i2c_master.v
module i2c_master (
    input wire clk,           // System clock
    input wire rst_n,         // Active-low reset
    input wire start,         // Start condition
    input wire read_write,    // 1 = Read, 0 = Write
    input wire [6:0] slave_addr,  // 7-bit slave address
    input wire [7:0] data_in, // Data to send (for write)
    input wire [6:0] reg_addr, 
    output reg [7:0] data_out, // Received data (for read)
    output reg busy,          // Busy flag
    output reg done,          // Transaction complete flag
    output wire scl,           // Serial Clock Line
    inout wire sda,           // Serial Data Line (Bidirectional)
    output [3:0] state_ind   // Indicating the current state of the FSM

	 );

    reg [3:0] state;
    reg [7:0] shift_reg;
    reg [3:0] bit_count;
    reg sda_out;
    reg sda_enable_master;
	 reg t_scl; 
	 
    assign sda = (sda_enable_master) ? sda_out : 1'bz;  // Open-drain SDA line
    assign scl = (busy) ? clk : 1; 
    // I2C State Machine Definitions
    localparam IDLE  = 4'b0000,
               START = 4'b0001,
               ADDR  = 4'b0010,
               RW    = 4'b0011,
               ACK1  = 4'b0100,
               WRITE = 4'b0101,
               ACK2  = 4'b0110,
               READ  = 4'b0111,
               STOP  = 4'b1000;
    
    // Initial Block to reset the signals
    initial begin
        busy = 0; 
        done = 0;
        t_scl = 0; 
		  end 

    // I2C State Machine
    always @(posedge clk or negedge rst_n) begin	
			
        if (!rst_n) begin
            // Resetting all internal registers and signals
            state <= IDLE;
            sda_out <= 1;
            sda_enable_master <= 1;
            busy <= 0;
            done <= 0;

            data_out <= 0;
      // SCL is high when idle
        end else begin
            case (state)
                IDLE: begin
                    busy <= 0;
                    done <= 0;
                    data_out <= 0;
                    // Keep SCL high when idle
                    if (start) begin
                        state <= START;
                        busy <= 1;
                    end
                end

                START: begin
                    sda_out <= 0;  // Start condition: SDA falls while SCL is high
                    sda_enable_master <= 1;
                    state <= ADDR;
                    shift_reg <= {slave_addr, read_write}; // Address + R/W bit
                    bit_count <= 8;
                end

                ADDR: begin
                    sda_enable_master <= 1;
                    if (bit_count > 0) begin
                        sda_out <= shift_reg[7];
                        shift_reg <= shift_reg << 1;
                        bit_count <= bit_count - 1;
                    end else begin
                        sda_enable_master <= 0; // Release SDA for ACK
                        state <= ACK1;
                    end
                end

               ACK1: begin
							sda_enable_master <= 0;  // Release SDA for ACK
							
							 // Introduce a small delay before checking for ACK (one clock cycle)
							 // Wait for the SCL to be high (slave should drive SDA low)
								  if (!sda) begin  // Slave ACK received (SDA low during SCL high)
										state <= (read_write) ? READ : WRITE;  // Proceed based on read/write
										shift_reg <= data_in;  // Load data for write operation
										bit_count <= 8;  // Reset bit count for next operation
								  end else begin  // NACK condition (SDA is high)
										state <= STOP;  // Stop the I2C transaction
								  end
						
end


                WRITE: begin
                    if (bit_count > 0) begin
                        sda_enable_master <= 1;
                        sda_out <= shift_reg[7];
                        shift_reg <= shift_reg << 1;
                        bit_count <= bit_count - 1;
                    end else begin
                        sda_enable_master <= 0; // Release SDA for ACK
                        state <= ACK2;
                    end
                end

                ACK2: begin
                    if (!sda && scl) begin // Slave ACK received (SDA low during SCL high)
                        state <= STOP;
                    end else if (scl) begin  // If SDA is high during SCL high, it's a NACK
                        state <= STOP;  // Handle NACK condition
                    end
                end

                READ: begin
                    if (bit_count > 0 && scl) begin
                        sda_enable_master <= 0; // Release SDA for reading
                        data_out <= {data_out[6:0], sda};
                        bit_count <= bit_count - 1;
                    end else if (bit_count == 0) begin
                        state <= STOP;
                    end
                end

                STOP: begin
                    sda_enable_master <= 1;
                    sda_out <= 0;  // Drive SDA low
                    #1; // Small delay to ensure SDA is stable before SCL changes
                    sda_out <= 1;  // Stop condition: SDA rises while SCL is high
                    done <= 1;
                    busy <= 0;
                    state <= IDLE;
                end
            endcase
        end
    end

    // Indicating the state (inverted state for clarity)
    assign state_ind = ~state;

endmodule

tb/interfaces/i2c_tb.v
`timescale 1ns / 1ps
`include "src/interfaces/i2c/i2c_master.v"

module tb_i2c_master;

    reg clk;
    reg rst_n;
    reg start;
    reg read_write;
    reg [6:0] slave_addr;
    reg [7:0] data_in;
    wire [7:0] data_out;
    wire busy, done;
    wire scl;
    wire sda;

    reg sda_slave;   // Simulated slave SDA line
    reg sda_from_slave; 


    // Instantiate I2C Master
    i2c_master uut(
        .clk(clk),
        .rst_n(rst_n),
        .start(start),
        .read_write(read_write),
        .slave_addr(slave_addr),
        .data_in(data_in),
        .data_out(data_out),
        .busy(busy),
        .done(done),
        .scl(scl),
        .sda(sda)
    );

    // Clock generator (100 MHz)
    always #5 clk = ~clk;

    initial begin
        // Initialize signals
        sda_slave = 0; 
        clk = 0;
        rst_n = 0;
        start = 0;
        read_write = 1  ;
        slave_addr = 7'b1010101; // Example address
        data_in = 8'h3C;
        sda_slave = 0;
        

        #20 rst_n = 1;  // Release reset

        // Read operation
        #50 read_write = 1;
        #10 start = 1;
        #10 start = 0;

        // Simulate data from slave
        #100
        sda_slave = 1; 
        sda_from_slave = 0; // ACK
        #10 sda_from_slave = 1; // Data bit 1
        #10 sda_from_slave = 0; // Data bit 0
        #10 sda_from_slave = 1; // Data bit 0
        #10 sda_from_slave = 1; // Data bit 0
        #10 sda_from_slave = 1; // Data bit 0
        #10 sda_from_slave = 1; // Data bit 0
        #10 sda_from_slave = 0; // Data bit 0
        #10 sda_from_slave = 1; // Stop

        #100
        // sda_slave = 0; 
        // sda_from_slave = 0; 
        #50
        sda_slave = 0; 

        $finish;
    end

    assign sda = (sda_slave) ? sda_from_slave :  1'bz ; // Open-drain emulation

    initial begin:TEST_BENCH
        $dumpfile("i2c_sim.vcd"); 
        $dumpvars(0, uut); 
    end 

endmodule

sim/waves/i2c_sim.vcd
$date
	Thu Mar  6 17:51:15 2025
$end
$version
	Icarus Verilog
$end
$timescale
	1ps
$end
$scope module tb_i2c_master $end
$scope module uut $end
$var wire 1 ! clk $end
$var wire 8 " data_in [7:0] $end
$var wire 1 # read_write $end
$var wire 7 $ reg_addr [6:0] $end
$var wire 1 % rst_n $end
$var wire 1 & sda $end
$var wire 7 ' slave_addr [6:0] $end
$var wire 1 ( start $end
$var wire 4 ) state_ind [3:0] $end
$var wire 1 * scl $end
$var parameter 4 + ACK1 $end
$var parameter 4 , ACK2 $end
$var parameter 4 - ADDR $end
$var parameter 4 . IDLE $end
$var parameter 4 / READ $end
$var parameter 4 0 RW $end
$var parameter 4 1 START $end
$var parameter 4 2 STOP $end
$var parameter 4 3 WRITE $end
$var reg 4 4 bit_count [3:0] $end
$var reg 1 5 busy $end
$var reg 8 6 data_out [7:0] $end
$var reg 1 7 done $end
$var reg 1 8 sda_enable_master $end
$var reg 1 9 sda_out $end
$var reg 8 : shift_reg [7:0] $end
$var reg 4 ; state [3:0] $end
$var reg 1 < t_scl $end
$upscope $end
$upscope $end
$enddefinitions $end
$comment Show the parameter values. $end
$dumpall
b101 3
b1000 2
b1 1
b11 0
b111 /
b0 .
b10 -
b110 ,
b100 +
$end
#0
$dumpvars
0<
b0 ;
bx :
19
18
07
b0 6
05
bx 4
1*
b1111 )
0(
b1010101 '
1&
0%
bz $
1#
b111100 "
0!
$end
#5000
1!
#10000
0!
#15000
1!
#20000
0!
1%
#25000
1!
#30000
0!
#35000
1!
#40000
0!
#45000
1!
#50000
0!
#55000
1!
#60000
0!
#65000
1!
#70000
0!
#75000
1!
#80000
0!
1(
#85000
b1110 )
15
b1 ;
1!
#90000
0*
0!
0(
#95000
b1101 )
0&
b1000 4
b10101011 :
b10 ;
09
1*
1!
#100000
0*
0!
#105000
1&
b111 4
b1010110 :
19
1*
1!
#110000
0*
0!
#115000
0&
b110 4
b10101100 :
09
1*
1!
#120000
0*
0!
#125000
1&
b101 4
b1011000 :
19
1*
1!
#130000
0*
0!
#135000
0&
b100 4
b10110000 :
09
1*
1!
#140000
0*
0!
#145000
1&
b11 4
b1100000 :
19
1*
1!
#150000
0*
0!
#155000
0&
b10 4
b11000000 :
09
1*
1!
#160000
0*
0!
#165000
1&
b1 4
b10000000 :
19
1*
1!
#170000
0*
0!
#175000
b0 4
b0 :
1*
1!
#180000
0*
0!
#185000
b1011 )
z&
b100 ;
08
1*
1!
#190000
0*
0&
0!
#195000
1*
1!
#200000
0*
1&
0!
#205000
1*
1!
#210000
0*
0&
0!
#215000
1*
1!
#220000
0*
1&
0!
#225000
1*
1!
#230000
0*
0!
#235000
1*
1!
#240000
0*
0!
#245000
1*
1!
#250000
0*
0!
#255000
1*
1!
#260000
0*
0&
0!
#265000
1*
1!
#270000
0*
1&
0!
#275000
1*
1!
#280000
0*
0!
#285000
1*
1!
#290000
0*
0!
#295000
1*
1!
#300000
0*
0!
#305000
1*
1!
#310000
0*
0!
#315000
1*
1!
#320000
0*
0!
#325000
1*
1!
#330000
0*
0!
#335000
1*
1!
#340000
0*
0!
#345000
1*
1!
#350000
0*
0!
#355000
1*
1!
#360000
0*
0!
#365000
1*
1!
#370000
0*
0!
#375000
1*
1!
#380000
0*
0!
#385000
1*
1!
#390000
0*
0!
#395000
1*
1!
#400000
0*
0!
#405000
1*
1!
#410000
0*
0!
#415000
1*
1!
#420000
0*
z&
0!
