src/interfaces/i2c/i2c_master.v
// This code implements the master controller for I2C Protocol
// author: Andrés Morales 


module i2c_master (
    input wire clk,           // System clock
    input wire rst_n,         // Active-low reset
    input wire start,         // Start condition
    input wire read_write,    // 1 = Read, 0 = Write
    input wire [6:0] slave_addr,  // 7-bit slave address
    input wire [7:0] data_in, // Data to send (for write)
    input wire [6:0] reg_addr, 
    output reg [7:0] data_out,// Received data (for read)
    output reg busy,          // Busy flag
    output reg done,          // Transaction complete flag
    output reg scl,           // Serial Clock Line
    inout wire sda            // Serial Data Line (Bidirectional)
);

    reg [3:0] state;
    reg [7:0] shift_reg;
    reg [3:0] bit_count;

    reg sda_out;
    // reg scl_follow; 
    reg sda_enable_master;

    assign sda = sda_enable_master ? sda_out : 1'bz;  // Open-drain SDA line
    // assign scl = scl_follow ? clk : 1'b1;  

    localparam IDLE  = 4'b0000,
               START = 4'b0001,
               ADDR  = 4'b0010,
               RW    = 4'b0011,
               ACK1  = 4'b0100,
               WRITE = 4'b0101,
               ACK2  = 4'b0110,
               READ  = 4'b0111,
               STOP  = 4'b1000;

    always @(clk) begin
        if (busy) scl = clk; 
        else scl = 1; 
    end 

    always @(posedge clk or negedge rst_n) begin
        if (!rst_n) begin
            $display("[i2c state] In reset"); 
            state <= IDLE;
            scl <= 1;
            // scl_follow <= 0; 
            sda_out <= 1;
            sda_enable_master <= 1;
            busy <= 0;
            done <= 0;
        end else begin
            case (state)
                IDLE: begin
                    $display("[i2c state] IDLE"); 
                    busy <= 0;
                    done <= 0;
                    data_out <= 0; 
                    if (start) begin
                        state <= START;
                        busy <= 1;
                    end
                end

                START: begin
                     $display("[i2c state] START"); 
                    sda_out <= 0; // Start condition
                    // scl_follow <= 1;
                    state <= ADDR;
                    sda_enable_master <= 1; 
                    shift_reg <= {slave_addr, read_write}; // Address + R/W bit
                    bit_count <= 8;
                end

                ADDR: begin
                    $display("[i2c state] ADDR"); 
                    if (bit_count > 0) begin
                    
                        sda_out <= shift_reg[7];
                        shift_reg <= shift_reg << 1;
                        bit_count <= bit_count - 1;
                    end else begin
                        $display("[i2c state] ADDR"); 
                        sda_enable_master <= 0; // Release SDA for ACK
                        state <= ACK1;
                    end
                end

                ACK1: begin
                    if (!sda) begin // Slave ACK received
                        
                        state <= (read_write) ? READ : WRITE;
                        shift_reg <= data_in;
                        bit_count <= 8;
                    end
                end

                WRITE: begin
                    if (bit_count > 0) begin
                        sda_out <= shift_reg[7];
                        shift_reg <= shift_reg << 1;
                        bit_count <= bit_count - 1;
                    end else begin
                        sda_enable_master <= 0; // Release SDA for ACK
                        state <= ACK2;
                    end
                end

                ACK2: begin
                    if (!sda) begin // Slave ACK received
                        state <= STOP;
                    end
                end

                READ: begin
                    if (bit_count > 0) begin
                        $display("count (%d) sda: %d",bit_count,  sda); 
                        sda_enable_master <= 0; // Release SDA for reading
                        data_out <= {data_out[6:0], sda};


                        bit_count <= bit_count - 1;
                    end else begin
                        state <= STOP;
                    end
                end

                STOP: begin
                    sda_enable_master <= 1;
                    sda_out <= 0;
                    scl <= 1;
                    sda_out <= 1; // Stop condition
                    done <= 1;
                    // scl_follow <= 0; 
                    busy <= 0;
                    state <= IDLE;
                end
            endcase
        end
    end

endmodule

src/modules/sensors/imu.v
`include "src/interfaces/i2c/i2c_master.v"

module imu  #(
    parameter DEV_ADDR = 7'h68 // Default addr 
) (
    input [7:0] reg_addr, 
    input start, 
    input clk, 
    inout wire sda, 
    input rst_n, 
    output [7:0] data_buff, // data leída 
    output busy, 
    output done,
    output slc
);

reg read_write; 
reg [1:0] state; //  

i2c_master uut(
    .clk(clk), 
    .rst_n(rst_n),
    .start(start), 
    .read_write(read_write), 
    .slave_addr(DEV_ADDR), 
    .scl(scl),
    .data_in(reg_addr),
    .data_out(data_buff), 
    .busy(busy),
    .done(done),
    .sda(sda)
); 

initial begin
    read_write = 1; // 1 read - 0 write
    state = 2'b00; 
end 



endmodule

tb/modules/imu_tb.v
`timescale 1ps/1ps
`include "src/modules/imu.v"

module imu_tb;

    reg clk, scl; 
    reg [7:0] reg_addr;  
    reg start; 
    reg rst_n; 
    inout wire sda;

    reg sda_write_slave; 
    reg sda_out; 

    wire [7:0] data_read;  
    wire busy; 
    wire done; 

    integer bit_count;

    // State encoding
    parameter IDLE            = 3'b000,
              RESET           = 3'b001,
              START_CONDITION = 3'b010,
              RECEIVE_ADDR    = 3'b011,
              SEND_ACK        = 3'b100,
              STOP_CONDITION  = 3'b101,
              FINISH          = 3'b110;

    reg [2:0] state; 

    // Clock generation
    initial clk = 0; 
    always #5 clk = ~clk; 

    // I2C SCL clock (20 ps period)
    initial scl = 0;
    always #10 scl = ~scl;

    // Open-drain emulation
    assign sda = (sda_write_slave) ? sda_out : 1'bz; 

    // Instantiate IMU module
    imu imu_uut(
        .reg_addr(reg_addr), 
        .start(start), 
        .clk(clk), 
        .rst_n(rst_n), 
        .data_buff(data_read), 
        .busy(busy), 
        .done(done),
        .sda(sda)
    ); 

    // Initial Conditions
    initial begin
        reg_addr = 8'b00100101;
        sda_write_slave = 0;
        sda_out = 0;
        start = 0;
        rst_n = 0;
        state = IDLE;  
        bit_count = 0;
    end

    // FSM Process
    always @(posedge clk) begin
        case (state)
            IDLE: begin
                state <= RESET;
            end

            RESET: begin
                rst_n <= 0;
                start <= 0;
                state <= START_CONDITION;
            end

            START_CONDITION: begin
                rst_n <= 1;
                start <= 1;
                bit_count <= 0;
                state <= RECEIVE_ADDR;
            end

            RECEIVE_ADDR: begin
                if (bit_count < 8) begin
                    bit_count <= bit_count + 1;
                end else begin
                    state <= SEND_ACK;
                    bit_count <= 0;
                end
            end

            SEND_ACK: begin
                sda_write_slave <= 1;
                sda_out <= 0; // ACK bit

                

                sda_write_slave <= 0; // Release line after ACK
                state <= STOP_CONDITION;
            end

            STOP_CONDITION: begin
                sda_out <= 1;  
                sda_write_slave <= 0;
                state <= FINISH;
            end

            FINISH: begin
                $display("End of transaction");
                $finish;
            end
        endcase
    end

    // VCD Dump for waveform analysis
    initial begin
        $dumpfile("imu_sim.vcd"); 
        $dumpvars(-1, imu_uut);  
    end

endmodule

sim/waves/imu_sim.vcd
$date
	Thu Feb 13 01:26:41 2025
$end
$version
	Icarus Verilog
$end
$timescale
	1ps
$end
$scope module imu_tb $end
$scope module imu_uut $end
$var wire 1 ! clk $end
$var wire 8 " reg_addr [7:0] $end
$var wire 1 # rst_n $end
$var wire 1 $ sda $end
$var wire 1 % slc $end
$var wire 1 & start $end
$var wire 1 ' scl $end
$var wire 1 ( done $end
$var wire 8 ) data_buff [7:0] $end
$var wire 1 * busy $end
$var parameter 7 + DEV_ADDR $end
$var reg 1 , read_write $end
$var reg 2 - state [1:0] $end
$scope module uut $end
$var wire 1 ! clk $end
$var wire 8 . data_in [7:0] $end
$var wire 1 , read_write $end
$var wire 7 / reg_addr [6:0] $end
$var wire 1 # rst_n $end
$var wire 1 $ sda $end
$var wire 7 0 slave_addr [6:0] $end
$var wire 1 & start $end
$var parameter 4 1 ACK1 $end
$var parameter 4 2 ACK2 $end
$var parameter 4 3 ADDR $end
$var parameter 4 4 IDLE $end
$var parameter 4 5 READ $end
$var parameter 4 6 RW $end
$var parameter 4 7 START $end
$var parameter 4 8 STOP $end
$var parameter 4 9 WRITE $end
$var reg 4 : bit_count [3:0] $end
$var reg 1 * busy $end
$var reg 8 ; data_out [7:0] $end
$var reg 1 ( done $end
$var reg 1 ' scl $end
$var reg 1 < sda_enable_master $end
$var reg 1 = sda_out $end
$var reg 8 > shift_reg [7:0] $end
$var reg 4 ? state [3:0] $end
$upscope $end
$upscope $end
$upscope $end
$enddefinitions $end
$comment Show the parameter values. $end
$dumpall
b101 9
b1000 8
b1 7
b11 6
b111 5
b0 4
b10 3
b110 2
b100 1
b1101000 +
$end
#0
$dumpvars
b0 ?
bx >
1=
1<
bx ;
bx :
b1101000 0
bz /
b100101 .
b0 -
1,
0*
bx )
0(
1'
0&
z%
1$
0#
b100101 "
0!
$end
#5
1!
#10
0!
#15
1!
#20
0!
#25
1&
1#
1!
#30
0!
#35
1*
b1 ?
b0 )
b0 ;
1!
#40
0'
0!
#45
0$
b1000 :
b11010001 >
b10 ?
0=
1'
1!
#50
0'
0!
#55
1$
b111 :
b10100010 >
1=
1'
1!
#60
0'
0!
#65
b110 :
b1000100 >
1'
1!
#70
0'
0!
#75
0$
b101 :
b10001000 >
0=
1'
1!
#80
0'
0!
#85
1$
b100 :
b10000 >
1=
1'
1!
#90
0'
0!
#95
0$
b11 :
b100000 >
0=
1'
1!
#100
0'
0!
#105
b10 :
b1000000 >
1'
1!
#110
0'
0!
#115
b1 :
b10000000 >
1'
1!
#120
0'
0!
#125
1$
b0 :
b0 >
1=
1'
1!
#130
0'
0!
#135
z$
b100 ?
0<
1'
1!
#140
0'
0!
#145
1'
1!
